hello_world/__init__.py
hello_world/cli.py
hello_world_deshitha1-0.2.dist-info/METADATA
hello_world_deshitha1-0.2.dist-info/WHEEL
hello_world_deshitha1-0.2.dist-info/entry_points.txt
hello_world_deshitha1-0.2.dist-info/top_level.txt
hello_world_deshitha1-0.2.dist-info/RECORD
